goodcrap/__init__.py
goodcrap/__main__.py
goodcrap/cli.py
goodcrap/fairker.py
goodcrap/goodcrap.py
goodcrap/imitator.py
goodcrap/random_mapper.py
goodcrap/crappers/__init__.py
goodcrap/crappers/queries.py
goodcrap/data_warehouses/__init__.py
goodcrap/data_warehouses/dimension_featurizer.py
goodcrap/databases/__init__.py
goodcrap/databases/database.py
goodcrap/databases/mysql.py
goodcrap/databases/queries.py
goodcrap/databases/snowflake.py
goodcrap/databases/sqlite.py
goodcrap/pipelines/__init__.py
goodcrap/pipelines/mage.py
goodcrap/pipelines/templates/__init__.py
goodcrap/pipelines/templates/data_exporter_mysql.py
goodcrap/pipelines/templates/data_loader.py
goodcrap/pipelines/templates/metadata.yaml
goodcrap/templates/__init__.py
goodcrap/templates/__pycache__/__init__.cpython-311.pyc
goodcrap/templates/data_warehouses/sales.crap_labels.json
goodcrap/templates/data_warehouses/sales.sql
goodcrap/templates/databases/customers_orders/customers_orders.crap_labels.json
goodcrap/templates/databases/customers_orders/customers_orders.sql
goodcrap/templates/tables/customers/customers.crap_labels.json
goodcrap/templates/tables/customers/customers.sql
goodcrap/templates/tables/orders/orders.crap_labels.json
goodcrap/templates/tables/orders/orders.sql
goodcrap-0.2.5.dist-info/LICENSE
goodcrap-0.2.5.dist-info/METADATA
goodcrap-0.2.5.dist-info/WHEEL
goodcrap-0.2.5.dist-info/entry_points.txt
goodcrap-0.2.5.dist-info/top_level.txt
goodcrap-0.2.5.dist-info/RECORD
