Metadata-Version: 2.1
Name: goodcrap
Version: 0.2.5
Summary: goodcrap creates tables, databases and csv files and fill them with random data
Home-page: https://github.com/goodcrap/goodcrap
Author: Sherif Abdulkader Tawfik Abbas
Author-email: sherif.tawfic@gmail.com
License: gpl-3.0
Keywords: ai,data engineering,fake data,data science
License-File: LICENSE
Requires-Dist: sqlalchemy
Requires-Dist: faker
Requires-Dist: pandas
Requires-Dist: numpy
Requires-Dist: jinja2
Requires-Dist: snowflake-sqlalchemy
